simpleaug/__init__.py
simpleaug/aug.py
simpleaug/temp.py
simpleaug/tool.py
SimpleAUG-0.0.4.dist-info/LICENSE.txt
SimpleAUG-0.0.4.dist-info/METADATA
SimpleAUG-0.0.4.dist-info/WHEEL
SimpleAUG-0.0.4.dist-info/top_level.txt
SimpleAUG-0.0.4.dist-info/RECORD
