Metadata-Version: 2.1
Name: SimpleAUG
Version: 0.0.4
Summary: A simpler imgaug tool
Author: Duyuxuan
Author-email: g2702922146@gmail.com
Classifier: Programming Language :: Python :: 3
Classifier: License :: OSI Approved :: MIT License
Classifier: Operating System :: OS Independent
Requires-Python: >=3.8
License-File: LICENSE.txt
